{ 
    "en":[
        { "url":"en/about", "label":"About Us"},
        { "url":"en/posts", "label":"Posts"},
        { "url":"", "label":"עברית"}
    ],
    "he":[
        { "url":"about", "label":"מי אנחנו?"},
        { "url":"messages", "label":"הודעות התנועה"},
        { "url":"position-papers", "label":"ניירות עמדה ומחקרים"},
        { "label":"בתקשורת", "subItems":[
            { "url":"posts", "label":"מאמרים"},
            { "url":"media", "label":"וידיאו"},
            { "url":"in-the-news", "label":"התנועה בחדשות"}
        ]},
        { "url":"contact-us", "label":"צור קשר"},
        { "url":"upcoming-events", "label":"אירועים קרובים"},
        { "url":"join-us", "label":"להצטרפות"},
        { "url":"donations", "label":"לתרומה"},
        { "url":"en", "label":"English"}
    ]
}