{"id":"%D7%A0%D7%99%D7%99%D7%A8%20%D7%A2%D7%9E%D7%93%D7%94%20%D7%97%D7%95%D7%A7%20%D7%A0%D7%95%D7%A8%D7%91%D7%92%D7%99%20%D7%9E%D7%95%D7%A8%D7%97%D7%91%20%D7%94%D7%9B%D7%A0%D7%A1%D7%AA%20%D7%9425","type":"papers","seo":{},"en":{},"date":"2023-01-09","body":"<p>הנחנו על שולחנה של ועדת החוקה, חוק ומשפט של הכנסת את חוות הדעת של התנועה להצעת חוק יסוד הכנסת: (תיקון – הפסקת חברות בכנסת של שר או סגן שר), הידועה בכינויה 'החוק הנורבגי המורחב'.&nbsp;</p>","paper":"papers/נייר עמדה חוק נורבגי מורחב הכנסת ה25/paper.pdf","title":"נייר עמדת התנועה בעניין החוק הנורבגי המורחב"}